[
    {
        "name": "Goal",
        "chest_unopened_img": "/images/items/close.png",
        "chest_opened_img": "/images/items/open.png",
        "overlay_background": "#000000",
        "access_rules": [
            " "
        ],
        "sections": [
            {
                "name": "Collect Memories",
                "access_rules": [],
                "visibility_rules": [],
                "item_count": 1
            },
            {
                "name": "Defeat Shinryu",
                "access_rules": [],
                "visibility_rules": [],
                "item_count": 1
            }
        ],
        "map_locations": [
            {
                "map": "Goal",
                "x": 328,
                "y": 1494,
                "size": 6
            }
        ]
    }
]