[
    {
        "name": "Urqopacha",
        "chest_unopened_img": "/images/items/close.png",
        "chest_opened_img": "/images/items/open.png",
        "overlay_background": "#000000",
        "access_rules": [
            " "
        ],
        "children": [
            {
                "name": "Worqor Zormor",
                "chest_unopened_img": "/images/items/close.png",
                "chest_opened_img": "/images/items/open.png",
                "overlay_background": "#000000",
                "access_rules": [
                    " "
                ],
                "sections": [
                    {
                        "name": "Worqor Zormor",
                        "access_rules": [],
                        "visibility_rules": [],
                        "item_count": 1
                    },
                    {
                        "name": "Worqor Zormor 2",
                        "access_rules": [],
                        "visibility_rules": [],
                        "item_count": 1
                    },
                    {
                        "name": "Worqor Zormor 3",
                        "access_rules": [],
                        "visibility_rules": [],
                        "item_count": 1
                    },
                    {
                        "name": "Worqor Zormor 4",
                        "access_rules": [],
                        "visibility_rules": [],
                        "item_count": 1
                    },
                    {
                        "name": "Worqor Zormor 5",
                        "access_rules": [],
                        "visibility_rules": [],
                        "item_count": 1
                    },
                    {
                        "name": "Worqor Zormor 6",
                        "access_rules": [],
                        "visibility_rules": [],
                        "item_count": 1
                    },
                    {
                        "name": "Worqor Zormor 7",
                        "access_rules": [],
                        "visibility_rules": [],
                        "item_count": 1
                    },
                    {
                        "name": "Worqor Zormor 8",
                        "access_rules": [],
                        "visibility_rules": [],
                        "item_count": 1
                    },
                    {
                        "name": "Worqor Zormor 9",
                        "access_rules": [],
                        "visibility_rules": [],
                        "item_count": 1
                    },
                    {
                        "name": "Worqor Zormor 10",
                        "access_rules": [],
                        "visibility_rules": [],
                        "item_count": 1
                    }
                ],
                "map_locations": [
                    {
                        "map": "Urqopacha",
                        "x": 999,
                        "y": 1338,
                        "size": 6
                    }
                ]
            },
            {
                "name": "Worqor Lar Dor",
                "chest_unopened_img": "/images/items/close.png",
                "chest_opened_img": "/images/items/open.png",
                "overlay_background": "#000000",
                "access_rules": [
                    " "
                ],
                "sections": [
                    {
                        "name": "Worqor Lar Dor",
                        "access_rules": [],
                        "visibility_rules": [],
                        "item_count": 1
                    },
                    {
                        "name": "Worqor Lar Dor (Extreme)",
                        "access_rules": [],
                        "visibility_rules": [],
                        "item_count": 1
                    }
                ],
                "map_locations": [
                    {
                        "map": "Urqopacha",
                        "x": 116,
                        "y": 2343,
                        "size": 6
                    }
                ]
            },
            {
                "name": "FATEs",
                "chest_unopened_img": "/images/items/close.png",
                "chest_opened_img": "/images/items/open.png",
                "overlay_background": "#000000",
                "access_rules": [
                    " "
                ],
                "sections": [
                    {
                        "name": "FATE #1",
                        "access_rules": [],
                        "visibility_rules": [],
                        "item_count": 1
                    },
                    {
                        "name": "FATE #2",
                        "access_rules": [],
                        "visibility_rules": [],
                        "item_count": 1
                    },
                    {
                        "name": "FATE #3",
                        "access_rules": [],
                        "visibility_rules": [],
                        "item_count": 1
                    },
                    {
                        "name": "FATE #4",
                        "access_rules": [],
                        "visibility_rules": [],
                        "item_count": 1
                    },
                    {
                        "name": "FATE #5",
                        "access_rules": [],
                        "visibility_rules": [],
                        "item_count": 1
                    },
                    {
                        "name": "FATE #6",
                        "access_rules": [],
                        "visibility_rules": [],
                        "item_count": 1
                    },
                    {
                        "name": "FATE #7",
                        "access_rules": [],
                        "visibility_rules": [],
                        "item_count": 1
                    },
                    {
                        "name": "FATE #8",
                        "access_rules": [],
                        "visibility_rules": [],
                        "item_count": 1
                    },
                    {
                        "name": "FATE #9",
                        "access_rules": [],
                        "visibility_rules": [],
                        "item_count": 1
                    },
                    {
                        "name": "FATE #10",
                        "access_rules": [],
                        "visibility_rules": [],
                        "item_count": 1
                    }
                ],
                "map_locations": [
                    {
                        "map": "Urqopacha",
                        "x": 2433,
                        "y": 640,
                        "size": 6
                    }
                ]
            },
            {
                "name": "Fire Suppression (FATE)",
                "chest_unopened_img": "/images/items/close.png",
                "chest_opened_img": "/images/items/open.png",
                "overlay_background": "#000000",
                "access_rules": [
                    " "
                ],
                "sections": [
                    {
                        "name": "Fire Suppression (FATE)",
                        "access_rules": [],
                        "visibility_rules": [],
                        "item_count": 1
                    }
                ],
                "map_locations": [
                    {
                        "map": "Urqopacha",
                        "x": 820,
                        "y": 2063,
                        "size": 6
                    }
                ]
            },
            {
                "name": "Panaq Attack (FATE)",
                "chest_unopened_img": "/images/items/close.png",
                "chest_opened_img": "/images/items/open.png",
                "overlay_background": "#000000",
                "access_rules": [
                    " "
                ],
                "sections": [
                    {
                        "name": "Panaq Attack (FATE)",
                        "access_rules": [],
                        "visibility_rules": [],
                        "item_count": 1
                    }
                ],
                "map_locations": [
                    {
                        "map": "Urqopacha",
                        "x": 1880,
                        "y": 808,
                        "size": 6
                    }
                ]
            },
            {
                "name": "Ratels So Ravenous (FATE)",
                "chest_unopened_img": "/images/items/close.png",
                "chest_opened_img": "/images/items/open.png",
                "overlay_background": "#000000",
                "access_rules": [
                    " "
                ],
                "sections": [
                    {
                        "name": "Ratels So Ravenous (FATE)",
                        "access_rules": [],
                        "visibility_rules": [],
                        "item_count": 1
                    }
                ],
                "map_locations": [
                    {
                        "map": "Urqopacha",
                        "x": 1889,
                        "y": 55,
                        "size": 6
                    }
                ]
            },
            {
                "name": "Birds Up (FATE)",
                "chest_unopened_img": "/images/items/close.png",
                "chest_opened_img": "/images/items/open.png",
                "overlay_background": "#000000",
                "access_rules": [
                    " "
                ],
                "sections": [
                    {
                        "name": "Birds Up (FATE)",
                        "access_rules": [],
                        "visibility_rules": [],
                        "item_count": 1
                    }
                ],
                "map_locations": [
                    {
                        "map": "Urqopacha",
                        "x": 915,
                        "y": 1669,
                        "size": 6
                    }
                ]
            },
            {
                "name": "Megamaguey Mayhem (FATE)",
                "chest_unopened_img": "/images/items/close.png",
                "chest_opened_img": "/images/items/open.png",
                "overlay_background": "#000000",
                "access_rules": [
                    " "
                ],
                "sections": [
                    {
                        "name": "Megamaguey Mayhem (FATE)",
                        "access_rules": [],
                        "visibility_rules": [],
                        "item_count": 1
                    }
                ],
                "map_locations": [
                    {
                        "map": "Urqopacha",
                        "x": 1082,
                        "y": 510,
                        "size": 6
                    }
                ]
            },
            {
                "name": "Pasture Expiration Date (FATE)",
                "chest_unopened_img": "/images/items/close.png",
                "chest_opened_img": "/images/items/open.png",
                "overlay_background": "#000000",
                "access_rules": [
                    " "
                ],
                "sections": [
                    {
                        "name": "Pasture Expiration Date (FATE)",
                        "access_rules": [],
                        "visibility_rules": [],
                        "item_count": 1
                    }
                ],
                "map_locations": [
                    {
                        "map": "Urqopacha",
                        "x": 154,
                        "y": 986,
                        "size": 6
                    }
                ]
            },
            {
                "name": "Too Irate to Migrate (FATE)",
                "chest_unopened_img": "/images/items/close.png",
                "chest_opened_img": "/images/items/open.png",
                "overlay_background": "#000000",
                "access_rules": [
                    " "
                ],
                "sections": [
                    {
                        "name": "Too Irate to Migrate (FATE)",
                        "access_rules": [],
                        "visibility_rules": [],
                        "item_count": 1
                    }
                ],
                "map_locations": [
                    {
                        "map": "Urqopacha",
                        "x": 1657,
                        "y": 1891,
                        "size": 6
                    }
                ]
            },
            {
                "name": "Weeding the Garden (FATE)",
                "chest_unopened_img": "/images/items/close.png",
                "chest_opened_img": "/images/items/open.png",
                "overlay_background": "#000000",
                "access_rules": [
                    " "
                ],
                "sections": [
                    {
                        "name": "Weeding the Garden (FATE)",
                        "access_rules": [],
                        "visibility_rules": [],
                        "item_count": 1
                    }
                ],
                "map_locations": [
                    {
                        "map": "Urqopacha",
                        "x": 700,
                        "y": 1625,
                        "size": 6
                    }
                ]
            },
            {
                "name": "Wolf Parade (FATE)",
                "chest_unopened_img": "/images/items/close.png",
                "chest_opened_img": "/images/items/open.png",
                "overlay_background": "#000000",
                "access_rules": [
                    " "
                ],
                "sections": [
                    {
                        "name": "Wolf Parade (FATE)",
                        "access_rules": [],
                        "visibility_rules": [],
                        "item_count": 1
                    }
                ],
                "map_locations": [
                    {
                        "map": "Urqopacha",
                        "x": 13,
                        "y": 718,
                        "size": 6
                    }
                ]
            },
            {
                "name": "A Valiant Duel (FATE)",
                "chest_unopened_img": "/images/items/close.png",
                "chest_opened_img": "/images/items/open.png",
                "overlay_background": "#000000",
                "access_rules": [
                    " "
                ],
                "sections": [
                    {
                        "name": "A Valiant Duel (FATE)",
                        "access_rules": [],
                        "visibility_rules": [],
                        "item_count": 1
                    }
                ],
                "map_locations": [
                    {
                        "map": "Urqopacha",
                        "x": 689,
                        "y": 597,
                        "size": 6
                    }
                ]
            },
            {
                "name": "Big Storm Coming (FATE)",
                "chest_unopened_img": "/images/items/close.png",
                "chest_opened_img": "/images/items/open.png",
                "overlay_background": "#000000",
                "access_rules": [
                    " "
                ],
                "sections": [
                    {
                        "name": "Big Storm Coming (FATE)",
                        "access_rules": [],
                        "visibility_rules": [],
                        "item_count": 1
                    }
                ],
                "map_locations": [
                    {
                        "map": "Urqopacha",
                        "x": 1969,
                        "y": 1451,
                        "size": 6
                    }
                ]
            },
            {
                "name": "By Your Powers Combined (FATE)",
                "chest_unopened_img": "/images/items/close.png",
                "chest_opened_img": "/images/items/open.png",
                "overlay_background": "#000000",
                "access_rules": [
                    " "
                ],
                "sections": [
                    {
                        "name": "By Your Powers Combined (FATE)",
                        "access_rules": [],
                        "visibility_rules": [],
                        "item_count": 1
                    }
                ],
                "map_locations": [
                    {
                        "map": "Urqopacha",
                        "x": 204,
                        "y": 228,
                        "size": 6
                    }
                ]
            },
            {
                "name": "Claws and Effect (FATE)",
                "chest_unopened_img": "/images/items/close.png",
                "chest_opened_img": "/images/items/open.png",
                "overlay_background": "#000000",
                "access_rules": [
                    " "
                ],
                "sections": [
                    {
                        "name": "Claws and Effect (FATE)",
                        "access_rules": [],
                        "visibility_rules": [],
                        "item_count": 1
                    }
                ],
                "map_locations": [
                    {
                        "map": "Urqopacha",
                        "x": 193,
                        "y": 1340,
                        "size": 6
                    }
                ]
            },
            {
                "name": "Gust Stop Already (FATE)",
                "chest_unopened_img": "/images/items/close.png",
                "chest_opened_img": "/images/items/open.png",
                "overlay_background": "#000000",
                "access_rules": [
                    " "
                ],
                "sections": [
                    {
                        "name": "Gust Stop Already (FATE)",
                        "access_rules": [],
                        "visibility_rules": [],
                        "item_count": 1
                    }
                ],
                "map_locations": [
                    {
                        "map": "Urqopacha",
                        "x": 2383,
                        "y": 2089,
                        "size": 6
                    }
                ]
            },
            {
                "name": "Lay Off the Horns (FATE)",
                "chest_unopened_img": "/images/items/close.png",
                "chest_opened_img": "/images/items/open.png",
                "overlay_background": "#000000",
                "access_rules": [
                    " "
                ],
                "sections": [
                    {
                        "name": "Lay Off the Horns (FATE)",
                        "access_rules": [],
                        "visibility_rules": [],
                        "item_count": 1
                    }
                ],
                "map_locations": [
                    {
                        "map": "Urqopacha",
                        "x": 677,
                        "y": 2497,
                        "size": 6
                    }
                ]
            },
            {
                "name": "Salty Showdown (FATE)",
                "chest_unopened_img": "/images/items/close.png",
                "chest_opened_img": "/images/items/open.png",
                "overlay_background": "#000000",
                "access_rules": [
                    " "
                ],
                "sections": [
                    {
                        "name": "Salty Showdown (FATE)",
                        "access_rules": [],
                        "visibility_rules": [],
                        "item_count": 1
                    }
                ],
                "map_locations": [
                    {
                        "map": "Urqopacha",
                        "x": 2277,
                        "y": 1319,
                        "size": 6
                    }
                ]
            },
            {
                "name": "So Long Suckers (FATE)",
                "chest_unopened_img": "/images/items/close.png",
                "chest_opened_img": "/images/items/open.png",
                "overlay_background": "#000000",
                "access_rules": [
                    " "
                ],
                "sections": [
                    {
                        "name": "So Long Suckers (FATE)",
                        "access_rules": [],
                        "visibility_rules": [],
                        "item_count": 1
                    }
                ],
                "map_locations": [
                    {
                        "map": "Urqopacha",
                        "x": 2194,
                        "y": 1779,
                        "size": 6
                    }
                ]
            },
            {
                "name": "Young Volcanoes (FATE)",
                "chest_unopened_img": "/images/items/close.png",
                "chest_opened_img": "/images/items/open.png",
                "overlay_background": "#000000",
                "access_rules": [
                    " "
                ],
                "sections": [
                    {
                        "name": "Young Volcanoes (FATE)",
                        "access_rules": [],
                        "visibility_rules": [],
                        "item_count": 1
                    }
                ],
                "map_locations": [
                    {
                        "map": "Urqopacha",
                        "x": 2212,
                        "y": 2160,
                        "size": 6
                    }
                ]
            },
            {
                "name": "Sunken Stars",
                "chest_unopened_img": "/images/items/close.png",
                "chest_opened_img": "/images/items/open.png",
                "overlay_background": "#000000",
                "access_rules": [
                    " "
                ],
                "sections": [
                    {
                        "name": "Sea Alpaca",
                        "access_rules": [],
                        "visibility_rules": [],
                        "item_count": 1
                    },
                    {
                        "name": "Marbled Hatchetfish",
                        "access_rules": [],
                        "visibility_rules": [],
                        "item_count": 1
                    },
                    {
                        "name": "Starsnipper",
                        "access_rules": [],
                        "visibility_rules": [],
                        "item_count": 1
                    },
                    {
                        "name": "Urqotrout",
                        "access_rules": [],
                        "visibility_rules": [],
                        "item_count": 1
                    },
                    {
                        "name": "Yok Huy Stonecutter",
                        "access_rules": [],
                        "visibility_rules": [],
                        "item_count": 1
                    },
                    {
                        "name": "Moongripper",
                        "access_rules": [],
                        "visibility_rules": [],
                        "item_count": 1
                    }
                ],
                "map_locations": [
                    {
                        "map": "Urqopacha",
                        "x": 253,
                        "y": 955,
                        "size": 6
                    }
                ]
            },
            {
                "name": "Chirwagur Lake",
                "chest_unopened_img": "/images/items/close.png",
                "chest_opened_img": "/images/items/open.png",
                "overlay_background": "#000000",
                "access_rules": [
                    " "
                ],
                "sections": [
                    {
                        "name": "Chirwagur Loach",
                        "access_rules": [],
                        "visibility_rules": [],
                        "item_count": 1
                    },
                    {
                        "name": "Alright Alright Alright",
                        "access_rules": [],
                        "visibility_rules": [],
                        "item_count": 1
                    },
                    {
                        "name": "Zorlortor",
                        "access_rules": [],
                        "visibility_rules": [],
                        "item_count": 1
                    },
                    {
                        "name": "Shooting Starscale",
                        "access_rules": [],
                        "visibility_rules": [],
                        "item_count": 1
                    }
                ],
                "map_locations": [
                    {
                        "map": "Urqopacha",
                        "x": 355,
                        "y": 503,
                        "size": 6
                    }
                ]
            },
            {
                "name": "Karvarhur the First",
                "chest_unopened_img": "/images/items/close.png",
                "chest_opened_img": "/images/items/open.png",
                "overlay_background": "#000000",
                "access_rules": [
                    " "
                ],
                "sections": [
                    {
                        "name": "First Feastfish",
                        "access_rules": [],
                        "visibility_rules": [],
                        "item_count": 1
                    }
                ],
                "map_locations": [
                    {
                        "map": "Urqopacha",
                        "x": 2266,
                        "y": 2242,
                        "size": 6
                    }
                ]
            }
        ]
    }
]